fairyspace/__about__.py
fairyspace/__init__.py
fairyspace/utils.py
fairyspace-0.0.1.dist-info/METADATA
fairyspace-0.0.1.dist-info/WHEEL
fairyspace-0.0.1.dist-info/licenses/LICENSE
fairyspace-0.0.1.dist-info/licenses/LICENSE.txt
fairyspace-0.0.1.dist-info/RECORD
