Metadata-Version: 2.4
Name: fairyspace
Version: 0.0.1
Project-URL: Documentation, https://github.com/devotefairy/fairyspace#readme
Project-URL: Issues, https://github.com/devotefairy/fairyspace/issues
Project-URL: Source, https://github.com/devotefairy/fairyspace
Author-email: allen <kycoolcool@gmail.com>
Maintainer-email: allen <kycoolcool@gmail.com>
License-Expression: MIT
License-File: LICENSE
License-File: LICENSE.txt
Classifier: Development Status :: 4 - Beta
Classifier: Programming Language :: Python
Classifier: Programming Language :: Python :: 3.11
Classifier: Programming Language :: Python :: 3.12
Classifier: Programming Language :: Python :: 3.13
Classifier: Programming Language :: Python :: Implementation :: CPython
Classifier: Programming Language :: Python :: Implementation :: PyPy
Requires-Python: >=3.11
Requires-Dist: django>=5.2
Requires-Dist: djangorestframework>=3.16
